steuerid/__init__.py
steuerid/exceptions.py
steuerid-2.0.0.dist-info/LICENSE
steuerid-2.0.0.dist-info/METADATA
steuerid-2.0.0.dist-info/WHEEL
steuerid-2.0.0.dist-info/RECORD
