Metadata-Version: 2.1
Name: steuerid
Version: 2.0.0
Summary: Validate German Tax-ID (Steuer-ID).
Author: Numan Ijaz
Author-email: numanijaz2@gmail.com
Requires-Python: >=3.10,<4.0
Classifier: Programming Language :: Python :: 3
Classifier: Programming Language :: Python :: 3.10
Classifier: Programming Language :: Python :: 3.11
Classifier: Programming Language :: Python :: 3.12
Classifier: Programming Language :: Python :: 3.13
